dcs_split_by_first_line/types.py
dcs_split_by_first_line-0.1.1.dist-info/METADATA
dcs_split_by_first_line-0.1.1.dist-info/WHEEL
dcs_split_by_first_line-0.1.1.dist-info/RECORD
