Metadata-Version: 2.1
Name: dcs-split-by-first-line
Version: 0.1.1
Summary: DCS - the most advanced admin editable setting
Home-page: https://github.com/oduvan/dcs-split-by-first-line
License: MIT
Keywords: Django,settings
Author: oduvan
Author-email: a.lyabah@checkio.org
Requires-Python: >=3.8
Classifier: Framework :: Django :: 3.2
Classifier: Framework :: Django :: 4
Classifier: Framework :: Django :: 4.0
Classifier: Framework :: Django :: 4.1
Classifier: Framework :: Django :: 4.2
Classifier: Framework :: Django :: 5.0
Classifier: License :: OSI Approved :: MIT License
Classifier: Programming Language :: Python :: 3
Classifier: Programming Language :: Python :: 3.8
Classifier: Programming Language :: Python :: 3.9
Classifier: Programming Language :: Python :: 3.10
Classifier: Programming Language :: Python :: 3.11
Classifier: Programming Language :: Python :: 3.12
Requires-Dist: django (>=3.2)
Requires-Dist: django-content-settings (>=0.22)
Project-URL: Repository, https://github.com/oduvan/dcs-split-by-first-line
